setup.py
startcast/__init__.py
startcast.egg-info/PKG-INFO
startcast.egg-info/SOURCES.txt
startcast.egg-info/dependency_links.txt
startcast.egg-info/entry_points.txt
startcast.egg-info/requires.txt
startcast.egg-info/top_level.txt