Metadata-Version: 1.1
Name: startcast
Version: 0.1.2
Summary: Start chromecast apps from command line
Home-page: https://github.com/diequeiroz/start-chromecast-CLI
Author: Diego Queiroz
Author-email: diego.queiroz@gmail.com
License: MIT
Keywords: chromecast application start cli
Platform: UNKNOWN
Classifier: Development Status :: 4 - Beta
Classifier: Intended Audience :: Developers
Classifier: Topic :: Software Development :: Build Tools
Classifier: License :: OSI Approved :: MIT License
Classifier: Programming Language :: Python :: 2
Classifier: Programming Language :: Python :: 2.6
Classifier: Programming Language :: Python :: 2.7
Classifier: Programming Language :: Python :: 3
Classifier: Programming Language :: Python :: 3.2
Classifier: Programming Language :: Python :: 3.3
Classifier: Programming Language :: Python :: 3.4
